{"no_of_atoms": 66, "centre_of_mass": [3.9997677164703974e-17, 6.5935, 1.6435465138533938], "maximum_diameter": {"diameter": 20.13688641244364, "atom_1": 0, "atom_2": 65}, "pore_diameter": {"diameter": -2.2481592621949806, "atom": 28}, "pore_volume": -5.94949144040474, "pore_diameter_opt": {"diameter": -2.2481592621949806, "atom_1": 28, "centre_of_mass": [3.9997677164703974e-17, 6.5935, 1.6435465138533938]}, "pore_volume_opt": -5.94949144040474, "windows": {"diameters": null, "centre_of_mass": null}}