{"no_of_atoms": 30, "centre_of_mass": [1.3480306007077974e-16, 10.227999999999998, 18.055], "maximum_diameter": {"diameter": 13.97706709313802, "atom_1": 18, "atom_2": 28}, "pore_diameter": {"diameter": -2.6109676812704286, "atom": 3}, "pore_volume": -9.319725279410507, "pore_diameter_opt": {"diameter": -2.6109676812704286, "atom_1": 3, "centre_of_mass": [1.3480306007077974e-16, 10.227999999999998, 18.055]}, "pore_volume_opt": -9.319725279410507, "windows": {"diameters": null, "centre_of_mass": null}}